<?xml version="1.0" encoding="UTF-8"?>
<DeploymentTargetType>
  <Name>OpenStack</Name>
  <Properties>
    <Group name="AuthParameters" displayName="Authentication Parameters">
      <Property name="user_name" displayName="Username" mode="MANDATORY" type="SingleLineText">
        <Description>Specify your OpenStack username.</Description>
      </Property>
      <Property name="password" displayName="Password" mode="MANDATORY" type="SingleLineText">
        <Description>Specify your OpenStack password.</Description>
      </Property>
      <Property name="tenant_name" displayName="Tenant Name" mode="EDITABLE" type="SingleLineText">
        <Description>Specify tenant name.</Description>
      </Property>
    </Group>
    <Group name="ServiceEndpoints" displayName="Service Endpoints">
      <Property name="identity_url" displayName="Identity URL" mode="EDITABLE" type="SingleLineText">
        <Description>Specify your OpenStack Identity URL.
				</Description>
      </Property>
      <Property name="compute_url" displayName="Compute URL" mode="EDITABLE" type="SingleLineText">
        <Description>Specify your OpenStack Compute URL.
				</Description>
      </Property>
    </Group>
  </Properties>
</DeploymentTargetType>